{
    "_id": "6263ef686ba1f6f2f7ff377d",
    "name": "Foreign Currency Market",
    "date": "2022-04-23T12:22:00.157Z",
    "currencies": [
        {
            "_id": "6263ef686ba1f6f2f7ff37a3",
            "ID": "R01115",
            "name": "Бразильский реал",
            "value": "15,8436",
            "numCode": "986",
            "charCode": "BRL",
            "nominal": "1",
            "__v": 0
        },
        {
            "_id": "6263ef686ba1f6f2f7ff37a9",
            "ID": "R01135",
            "name": "Венгерских форинтов",
            "value": "21,3914",
            "numCode": "348",
            "charCode": "HUF",
            "nominal": "100",
            "__v": 0
        },
        {
            "_id": "6263ef686ba1f6f2f7ff37af",
            "ID": "R01035",
            "name": "Фунт стерлингов Соединенного королевства",
            "value": "95,7844",
            "numCode": "826",
            "charCode": "GBP",
            "nominal": "1",
            "__v": 0
        },
        {
            "_id": "6263ef686ba1f6f2f7ff37b1",
            "ID": "R01215",
            "name": "Датская крона",
            "value": "10,7556",
            "numCode": "208",
            "charCode": "DKK",
            "nominal": "1",
            "__v": 0
        },
        {
            "_id": "6263ef686ba1f6f2f7ff37b5",
            "ID": "R01200",
            "name": "Гонконгских долларов",
            "value": "93,8641",
            "numCode": "344",
            "charCode": "HKD",
            "nominal": "10",
            "__v": 0
        },
        {
            "_id": "6263ef686ba1f6f2f7ff37c9",
            "ID": "R01720",
            "name": "Украинских гривен",
            "value": "24,2913",
            "numCode": "980",
            "charCode": "UAH",
            "nominal": "10",
            "__v": 0
        },
        {
            "_id": "6263ef686ba1f6f2f7ff37a7",
            "ID": "R01270",
            "name": "Индийских рупий",
            "value": "96,4319",
            "numCode": "356",
            "charCode": "INR",
            "nominal": "100",
            "__v": 0
        },
        {
            "_id": "6263ef686ba1f6f2f7ff37b9",
            "ID": "R01335",
            "name": "Казахстанских тенге",
            "value": "16,5537",
            "numCode": "398",
            "charCode": "KZT",
            "nominal": "100",
            "__v": 0
        },
        {
            "_id": "6263ef686ba1f6f2f7ff37cf",
            "ID": "R01370",
            "name": "Киргизских сомов",
            "value": "90,8983",
            "numCode": "417",
            "charCode": "KGS",
            "nominal": "100",
            "__v": 0
        },
        {
            "_id": "6263ef686ba1f6f2f7ff37bf",
            "ID": "R01500",
            "name": "Молдавских леев",
            "value": "39,7791",
            "numCode": "498",
            "charCode": "MDL",
            "nominal": "10",
            "__v": 0
        },
        {
            "_id": "6263ef686ba1f6f2f7ff37b3",
            "ID": "R01090B",
            "name": "Белорусский рубль",
            "value": "27,0707",
            "numCode": "933",
            "charCode": "BYN",
            "nominal": "1",
            "__v": 0
        },
        {
            "_id": "6263ef686ba1f6f2f7ff37b7",
            "ID": "R01060",
            "name": "Армянских драмов",
            "value": "15,7304",
            "numCode": "051",
            "charCode": "AMD",
            "nominal": "100",
            "__v": 0
        },
        {
            "_id": "6263ef686ba1f6f2f7ff37c5",
            "ID": "R01770",
            "name": "Шведских крон",
            "value": "77,0800",
            "numCode": "752",
            "charCode": "SEK",
            "nominal": "10",
            "__v": 0
        },
        {
            "_id": "6263ef686ba1f6f2f7ff37cd",
            "ID": "R01717",
            "name": "Узбекских сумов",
            "value": "65,0367",
            "numCode": "860",
            "charCode": "UZS",
            "nominal": "10000",
            "__v": 0
        },
        {
            "_id": "6263ef686ba1f6f2f7ff37c7",
            "ID": "R01760",
            "name": "Чешских крон",
            "value": "32,6907",
            "numCode": "203",
            "charCode": "CZK",
            "nominal": "10",
            "__v": 0
        },
        {
            "_id": "6263ef686ba1f6f2f7ff37db",
            "ID": "R01670",
            "name": "Таджикских сомони",
            "value": "58,7687",
            "numCode": "972",
            "charCode": "TJS",
            "nominal": "10",
            "__v": 0
        },
        {
            "_id": "6263ef686ba1f6f2f7ff37ad",
            "ID": "R01100",
            "name": "Болгарский лев",
            "value": "40,9157",
            "numCode": "975",
            "charCode": "BGN",
            "nominal": "1",
            "__v": 0
        },
        {
            "_id": "6263ef686ba1f6f2f7ff37d5",
            "ID": "R01710A",
            "name": "Новый туркменский манат",
            "value": "21,0014",
            "numCode": "934",
            "charCode": "TMT",
            "nominal": "1",
            "__v": 0
        },
        {
            "_id": "6263ef686ba1f6f2f7ff37cb",
            "ID": "R01700J",
            "name": "Турецких лир",
            "value": "49,9351",
            "numCode": "949",
            "charCode": "TRY",
            "nominal": "10",
            "__v": 0
        },
        {
            "_id": "6263ef686ba1f6f2f7ff37d1",
            "ID": "R01375",
            "name": "Китайский юань",
            "value": "11,3057",
            "numCode": "156",
            "charCode": "CNY",
            "nominal": "1",
            "__v": 0
        },
        {
            "_id": "6263ef686ba1f6f2f7ff37d3",
            "ID": "R01589",
            "name": "СДР (специальные права заимствования)",
            "value": "99,9734",
            "numCode": "960",
            "charCode": "XDR",
            "nominal": "1",
            "__v": 0
        },
        {
            "_id": "6263ef686ba1f6f2f7ff37bb",
            "ID": "R01350",
            "name": "Канадский доллар",
            "value": "58,6679",
            "numCode": "124",
            "charCode": "CAD",
            "nominal": "1",
            "__v": 0
        },
        {
            "_id": "6263ef686ba1f6f2f7ff37bd",
            "ID": "R01010",
            "name": "Австралийский доллар",
            "value": "53,9159",
            "numCode": "036",
            "charCode": "AUD",
            "nominal": "1",
            "__v": 0
        },
        {
            "_id": "6263ef686ba1f6f2f7ff37ab",
            "ID": "R01239",
            "name": "Евро",
            "value": "80,0249",
            "numCode": "978",
            "charCode": "EUR",
            "nominal": "1",
            "__v": 0
        },
        {
            "_id": "6263ef686ba1f6f2f7ff37c3",
            "ID": "R01625",
            "name": "Сингапурский доллар",
            "value": "53,8814",
            "numCode": "702",
            "charCode": "SGD",
            "nominal": "1",
            "__v": 0
        },
        {
            "_id": "6263ef686ba1f6f2f7ff37d7",
            "ID": "R01775",
            "name": "Швейцарский франк",
            "value": "76,9283",
            "numCode": "756",
            "charCode": "CHF",
            "nominal": "1",
            "__v": 0
        },
        {
            "_id": "6263ef686ba1f6f2f7ff37a5",
            "ID": "R01235",
            "name": "Доллар США",
            "value": "73,5050",
            "numCode": "840",
            "charCode": "USD",
            "nominal": "1",
            "__v": 0
        },
        {
            "_id": "6263ef686ba1f6f2f7ff37a1",
            "ID": "R01020A",
            "name": "Азербайджанский манат",
            "value": "43,2382",
            "numCode": "944",
            "charCode": "AZN",
            "nominal": "1",
            "__v": 0
        },
        {
            "_id": "6263ef686ba1f6f2f7ff37f1",
            "ID": "R01810",
            "name": "Южноафриканских рэндов",
            "value": "47,4382",
            "numCode": "710",
            "charCode": "ZAR",
            "nominal": "10",
            "__v": 0
        },
        {
            "_id": "6263ef686ba1f6f2f7ff37e3",
            "ID": "R01820",
            "name": "Японских иен",
            "value": "57,1534",
            "numCode": "392",
            "charCode": "JPY",
            "nominal": "100",
            "__v": 0
        },
        {
            "_id": "6263ef686ba1f6f2f7ff37d9",
            "ID": "R01585F",
            "name": "Румынский лей",
            "value": "16,2188",
            "numCode": "946",
            "charCode": "RON",
            "nominal": "1",
            "__v": 0
        },
        {
            "_id": "6263ef686ba1f6f2f7ff37dd",
            "ID": "R01535",
            "name": "Норвежских крон",
            "value": "83,5436",
            "numCode": "578",
            "charCode": "NOK",
            "nominal": "10",
            "__v": 0
        },
        {
            "_id": "6263ef686ba1f6f2f7ff37e5",
            "ID": "R01815",
            "name": "Вон Республики Корея",
            "value": "59,3213",
            "numCode": "410",
            "charCode": "KRW",
            "nominal": "1000",
            "__v": 0
        },
        {
            "_id": "6263ef686ba1f6f2f7ff37c1",
            "ID": "R01565",
            "name": "Польский злотый",
            "value": "17,1737",
            "numCode": "985",
            "charCode": "PLN",
            "nominal": "1",
            "__v": 0
        }
    ],
    "__v": 34
}